combina_cpp_and_py/__init__.py
combina_cpp_and_py/check_code.py
combina_cpp_and_py/write_cpp_combina_to_py.py
combina_cpp_and_py/include/combine.h
combina_cpp_and_py-0.4.0.1.dist-info/LICENSE
combina_cpp_and_py-0.4.0.1.dist-info/METADATA
combina_cpp_and_py-0.4.0.1.dist-info/WHEEL
combina_cpp_and_py-0.4.0.1.dist-info/top_level.txt
combina_cpp_and_py-0.4.0.1.dist-info/RECORD
