Metadata-Version: 2.1
Name: combina_cpp_and_py
Version: 0.4.0.1
Summary: Combina C++ and Python code
Home-page: https://github.com/Locked-chess-official/cpppy
Author: Locked-chess-official
Author-email: 13140752715@163.com
Platform: windows
License-File: LICENSE
